drmatlantis/__init__.py
drmatlatnis-0.1.dist-info/METADATA
drmatlatnis-0.1.dist-info/WHEEL
drmatlatnis-0.1.dist-info/top_level.txt
drmatlatnis-0.1.dist-info/RECORD
