Metadata-Version: 2.1
Name: drmatlatnis
Version: 0.1
Summary: Dr. MATLANTIS server tool that connects local chatbot to MATLANTIS server
Author: Hristo Todorov
Author-email: hristo@so-ti.com
License: MIT
Requires-Dist: anywidget
Requires-Dist: traitlets
Requires-Dist: ipylab
Requires-Dist: IPython
